saic_ismart_client/__init__.py
saic_ismart_client/abrp_api.py
saic_ismart_client/common_model.py
saic_ismart_client/exceptions.py
saic_ismart_client/message_decoder.py
saic_ismart_client/saic_api.py
saic_ismart_client/ASN.1_schema/v1_1/ApplicationData.asn1
saic_ismart_client/ASN.1_schema/v1_1/MP_DispatcherBody.asn1
saic_ismart_client/ASN.1_schema/v1_1/MP_DispatcherHeader.asn1
saic_ismart_client/ASN.1_schema/v2_1/ApplicationData.asn1
saic_ismart_client/ASN.1_schema/v2_1/MP_DispatcherBody.asn1
saic_ismart_client/ASN.1_schema/v2_1/MP_DispatcherHeader.asn1
saic_ismart_client/ASN.1_schema/v3_0/ApplicationData.asn1
saic_ismart_client/ASN.1_schema/v3_0/MP_DispatcherBody.asn1
saic_ismart_client/ASN.1_schema/v3_0/MP_DispatcherHeader.asn1
saic_ismart_client/ota_v1_1/Message.py
saic_ismart_client/ota_v1_1/__init__.py
saic_ismart_client/ota_v1_1/data_model.py
saic_ismart_client/ota_v2_1/Message.py
saic_ismart_client/ota_v2_1/__init__.py
saic_ismart_client/ota_v2_1/data_model.py
saic_ismart_client/ota_v3_0/Message.py
saic_ismart_client/ota_v3_0/__init__.py
saic_ismart_client/ota_v3_0/data_model.py
saic_ismart_client/rest_v2/__init__.py
saic_ismart_client/rest_v2/api.py
saic_ismart_client/rest_v2/model.py
saic_ismart_client-1.7.2.dist-info/LICENSE
saic_ismart_client-1.7.2.dist-info/METADATA
saic_ismart_client-1.7.2.dist-info/WHEEL
saic_ismart_client-1.7.2.dist-info/top_level.txt
saic_ismart_client-1.7.2.dist-info/RECORD
