Metadata-Version: 2.1
Name: saic-ismart-client
Version: 1.7.2
Summary: SAIC client library (MG iSMART)
Author-email: Thomas Salm <saic-python-client@devtom.de>
Project-URL: Homepage, https://github.com/SAIC-iSmart-API/saic-python-client
Project-URL: Bug Tracker, https://github.com/SAIC-iSmart-API/saic-python-client/issues
Classifier: Programming Language :: Python :: 3
Classifier: License :: OSI Approved :: MIT License
Classifier: Operating System :: OS Independent
Requires-Python: >=3.9
License-File: LICENSE
Requires-Dist: asn1tools >=0.166.0
Requires-Dist: requests >=2.31.0
Requires-Dist: urllib3 >=2.0.3
